{"UID": {"0mihi0": {"text": "걸플갤", "color": "#cc6ab5"}, "0qc1pyiceo40": {"text": "걸플갤", "color": "#cc6ab5"}, "12dc3": {"text": "걸플갤", "color": "#cc6ab5"}, "19tzoj6qamqc": {"text": "걸플갤", "color": "#cc6ab5"}, "20dmo": {"text": "걸플갤", "color": "#cc6ab5"}, "2bml62gd856a": {"text": "걸플갤", "color": "#cc6ab5"}, "38skmzweu7am": {"text": "걸플갤", "color": "#cc6ab5"}, "4cf1yt9ejhtf": {"text": "걸플갤", "color": "#cc6ab5"}, "50vs50": {"text": "걸플갤", "color": "#cc6ab5"}, "56n33qnfm9cwlsg": {"text": "걸플갤", "color": "#cc6ab5"}, "5cv6bcu68tqq": {"text": "걸플갤", "color": "#cc6ab5"}, "5kq08nd797h4": {"text": "걸플갤", "color": "#cc6ab5"}, "5qdb5l0b5vs6": {"text": "걸플갤", "color": "#cc6ab5"}, "5qoqti3h6b7v": {"text": "걸플갤", "color": "#cc6ab5"}, "6x500zjll6sr": {"text": "걸플갤", "color": "#cc6ab5"}, "7fr2wutcd4p9": {"text": "걸플갤", "color": "#cc6ab5"}, "8888zzzzq": {"text": "걸플갤", "color": "#cc6ab5"}, "8fqej8pevcl1": {"text": "걸플갤", "color": "#cc6ab5"}, "8mqhvg6fdm1m": {"text": "걸플갤", "color": "#cc6ab5"}, "92uwl2vxpghr": {"text": "걸플갤", "color": "#cc6ab5"}, "abandon3905": {"text": "걸플갤", "color": "#cc6ab5"}, "abcd12344567": {"text": "걸플갤", "color": "#cc6ab5"}, "abcde77123": {"text": "걸플갤", "color": "#cc6ab5"}, "abcui2589": {"text": "걸플갤", "color": "#cc6ab5"}, "aboard9326": {"text": "걸플갤", "color": "#cc6ab5"}, "acceard": {"text": "걸플갤", "color": "#cc6ab5"}, "accent5049": {"text": "걸플갤", "color": "#cc6ab5"}, "accord2616": {"text": "걸플갤", "color": "#cc6ab5"}, "achieve1548": {"text": "걸플갤", "color": "#cc6ab5"}, "actual9855": {"text": "걸플갤", "color": "#cc6ab5"}, "advanced9372": {"text": "걸플갤", "color": "#cc6ab5"}, "ahngg": {"text": "걸플갤", "color": "#cc6ab5"}, "aimi0904": {"text": "걸플갤", "color": "#cc6ab5"}, "alalsk2": {"text": "걸플갤", "color": "#cc6ab5"}, "alcoholic000": {"text": "걸플갤", "color": "#cc6ab5"}, "alike5687": {"text": "걸플갤", "color": "#cc6ab5"}, "along3120": {"text": "걸플갤", "color": "#cc6ab5"}, "along7804": {"text": "걸플갤", "color": "#cc6ab5"}, "alphabet3446": {"text": "걸플갤", "color": "#cc6ab5"}, "alsry1598": {"text": "걸플갤", "color": "#cc6ab5"}, "amaze0227": {"text": "걸플갤", "color": "#cc6ab5"}, "ancient4455": {"text": "걸플갤", "color": "#cc6ab5"}, "andlau3": {"text": "걸플갤", "color": "#cc6ab5"}, "andlau5": {"text": "걸플갤", "color": "#cc6ab5"}, "angel1831": {"text": "걸플갤", "color": "#cc6ab5"}, "angry2823": {"text": "걸플갤", "color": "#cc6ab5"}, "another4637": {"text": "걸플갤", "color": "#cc6ab5"}, "antiques6067": {"text": "걸플갤", "color": "#cc6ab5"}, "antiques9282": {"text": "걸플갤", "color": "#cc6ab5"}, "anything2590": {"text": "걸플갤", "color": "#cc6ab5"}, "ap5pfl1uvvq4": {"text": "걸플갤", "color": "#cc6ab5"}, "apology5142": {"text": "걸플갤", "color": "#cc6ab5"}, "approve2087": {"text": "걸플갤", "color": "#cc6ab5"}, "area3949": {"text": "걸플갤", "color": "#cc6ab5"}, "arginine3": {"text": "걸플갤", "color": "#cc6ab5"}, "arinbbangya": {"text": "걸플갤", "color": "#cc6ab5"}, "asdfdsa111": {"text": "걸플갤", "color": "#cc6ab5"}, "assa2848": {"text": "걸플갤", "color": "#cc6ab5"}, "assist1055": {"text": "걸플갤", "color": "#cc6ab5"}, "atfgvm0101": {"text": "걸플갤", "color": "#cc6ab5"}, "attain5916": {"text": "걸플갤", "color": "#cc6ab5"}, "auto3525": {"text": "걸플갤", "color": "#cc6ab5"}, "average7234": {"text": "걸플갤", "color": "#cc6ab5"}, "awake0233": {"text": "걸플갤", "color": "#cc6ab5"}, "away6094": {"text": "걸플갤", "color": "#cc6ab5"}, "b24t5lk0y1rk": {"text": "걸플갤", "color": "#cc6ab5"}, "babysit0816": {"text": "걸플갤", "color": "#cc6ab5"}, "back7096": {"text": "걸플갤", "color": "#cc6ab5"}, "bakapple": {"text": "걸플갤", "color": "#cc6ab5"}, "bake5135": {"text": "걸플갤", "color": "#cc6ab5"}, "bank8730": {"text": "걸플갤", "color": "#cc6ab5"}, "barber6864": {"text": "걸플갤", "color": "#cc6ab5"}, "barber9293": {"text": "걸플갤", "color": "#cc6ab5"}, "basket1402": {"text": "걸플갤", "color": "#cc6ab5"}, "batarkerei": {"text": "걸플갤", "color": "#cc6ab5"}, "battle7410": {"text": "걸플갤", "color": "#cc6ab5"}, "bayrlnk": {"text": "걸플갤", "color": "#cc6ab5"}, "bbzz11": {"text": "걸플갤", "color": "#cc6ab5"}, "bd4a89h2bhs8": {"text": "걸플갤", "color": "#cc6ab5"}, "beach8372": {"text": "걸플갤", "color": "#cc6ab5"}, "beast3806": {"text": "걸플갤", "color": "#cc6ab5"}, "become5289": {"text": "걸플갤", "color": "#cc6ab5"}, "bedding7708": {"text": "걸플갤", "color": "#cc6ab5"}, "beef8745": {"text": "걸플갤", "color": "#cc6ab5"}, "beer7665": {"text": "걸플갤", "color": "#cc6ab5"}, "behavior6066": {"text": "걸플갤", "color": "#cc6ab5"}, "beneath1057": {"text": "걸플갤", "color": "#cc6ab5"}, "benji1373": {"text": "걸플갤", "color": "#cc6ab5"}, "beyond5800": {"text": "걸플갤", "color": "#cc6ab5"}, "bike0780": {"text": "걸플갤", "color": "#cc6ab5"}, "bisu0735": {"text": "걸플갤", "color": "#cc6ab5"}, "bitter1338": {"text": "걸플갤", "color": "#cc6ab5"}, "blender5359": {"text": "걸플갤", "color": "#cc6ab5"}, "bless1543": {"text": "걸플갤", "color": "#cc6ab5"}, "bless1973": {"text": "걸플갤", "color": "#cc6ab5"}, "blonde8926": {"text": "걸플갤", "color": "#cc6ab5"}, "bloom4405": {"text": "걸플갤", "color": "#cc6ab5"}, "blow7976": {"text": "걸플갤", "color": "#cc6ab5"}, "bluebirdbd": {"text": "걸플갤", "color": "#cc6ab5"}, "bmwbmw123": {"text": "걸플갤", "color": "#cc6ab5"}, "body1077": {"text": "걸플갤", "color": "#cc6ab5"}, "bookconcert": {"text": "걸플갤", "color": "#cc6ab5"}, "boom6866": {"text": "걸플갤", "color": "#cc6ab5"}, "boss9248": {"text": "걸플갤", "color": "#cc6ab5"}, "brake6361": {"text": "걸플갤", "color": "#cc6ab5"}, "brave7200": {"text": "걸플갤", "color": "#cc6ab5"}, "brazil8231": {"text": "걸플갤", "color": "#cc6ab5"}, "breeze4471": {"text": "걸플갤", "color": "#cc6ab5"}, "bright1673": {"text": "걸플갤", "color": "#cc6ab5"}, "broth0441": {"text": "걸플갤", "color": "#cc6ab5"}, "brown0396": {"text": "걸플갤", "color": "#cc6ab5"}, "bullet2239": {"text": "걸플갤", "color": "#cc6ab5"}, "bulovalova": {"text": "걸플갤", "color": "#cc6ab5"}, "bundle4489": {"text": "걸플갤", "color": "#cc6ab5"}, "butter5611": {"text": "걸플갤", "color": "#cc6ab5"}, "c4rkdnine7sk": {"text": "걸플갤", "color": "#cc6ab5"}, "c9ath8qqrxh6": {"text": "걸플갤", "color": "#cc6ab5"}, "cabbage3871": {"text": "걸플갤", "color": "#cc6ab5"}, "camel1031": {"text": "걸플갤", "color": "#cc6ab5"}, "campaign4600": {"text": "걸플갤", "color": "#cc6ab5"}, "canadian8786": {"text": "걸플갤", "color": "#cc6ab5"}, "capable1755": {"text": "걸플갤", "color": "#cc6ab5"}, "capital7595": {"text": "걸플갤", "color": "#cc6ab5"}, "caution7576": {"text": "걸플갤", "color": "#cc6ab5"}, "ceiling8095": {"text": "걸플갤", "color": "#cc6ab5"}, "ceiling8876": {"text": "걸플갤", "color": "#cc6ab5"}, "cellist3733": {"text": "걸플갤", "color": "#cc6ab5"}, "ceremony6528": {"text": "걸플갤", "color": "#cc6ab5"}, "chairman2700": {"text": "걸플갤", "color": "#cc6ab5"}, "chance2998": {"text": "걸플갤", "color": "#cc6ab5"}, "charm8156": {"text": "걸플갤", "color": "#cc6ab5"}, "chat5428": {"text": "걸플갤", "color": "#cc6ab5"}, "cheese9894": {"text": "걸플갤", "color": "#cc6ab5"}, "chick6336": {"text": "걸플갤", "color": "#cc6ab5"}, "chicken7791": {"text": "걸플갤", "color": "#cc6ab5"}, "chillsung2": {"text": "걸플갤", "color": "#cc6ab5"}, "chin4413": {"text": "걸플갤", "color": "#cc6ab5"}, "chlwltn4444": {"text": "걸플갤", "color": "#cc6ab5"}, "chop9678": {"text": "걸플갤", "color": "#cc6ab5"}, "chore4131": {"text": "걸플갤", "color": "#cc6ab5"}, "church0509": {"text": "걸플갤", "color": "#cc6ab5"}, "civil2645": {"text": "걸플갤", "color": "#cc6ab5"}, "ckduddn12": {"text": "걸플갤", "color": "#cc6ab5"}, "clap5855": {"text": "걸플갤", "color": "#cc6ab5"}, "clarify7901": {"text": "걸플갤", "color": "#cc6ab5"}, "clfmvm34": {"text": "걸플갤", "color": "#cc6ab5"}, "click5654": {"text": "걸플갤", "color": "#cc6ab5"}, "climbing8100": {"text": "걸플갤", "color": "#cc6ab5"}, "clip1932": {"text": "걸플갤", "color": "#cc6ab5"}, "clock2877": {"text": "걸플갤", "color": "#cc6ab5"}, "close8431": {"text": "걸플갤", "color": "#cc6ab5"}, "closet5847": {"text": "걸플갤", "color": "#cc6ab5"}, "coast2091": {"text": "걸플갤", "color": "#cc6ab5"}, "coke8379": {"text": "걸플갤", "color": "#cc6ab5"}, "college0170": {"text": "걸플갤", "color": "#cc6ab5"}, "college4961": {"text": "걸플갤", "color": "#cc6ab5"}, "command6388": {"text": "걸플갤", "color": "#cc6ab5"}, "compact3992": {"text": "걸플갤", "color": "#cc6ab5"}, "compound2847": {"text": "걸플갤", "color": "#cc6ab5"}, "comprise4058": {"text": "걸플갤", "color": "#cc6ab5"}, "concerto8143": {"text": "걸플갤", "color": "#cc6ab5"}, "conform9302": {"text": "걸플갤", "color": "#cc6ab5"}, "conquer8485": {"text": "걸플갤", "color": "#cc6ab5"}, "conserve1265": {"text": "걸플갤", "color": "#cc6ab5"}, "consistent": {"text": "걸플갤", "color": "#cc6ab5"}, "constanthi": {"text": "걸플갤", "color": "#cc6ab5"}, "contend1772": {"text": "걸플갤", "color": "#cc6ab5"}, "contend6978": {"text": "걸플갤", "color": "#cc6ab5"}, "contest0976": {"text": "걸플갤", "color": "#cc6ab5"}, "contract2748": {"text": "걸플갤", "color": "#cc6ab5"}, "contract5613": {"text": "걸플갤", "color": "#cc6ab5"}, "cookie7946": {"text": "걸플갤", "color": "#cc6ab5"}, "coolvent": {"text": "걸플갤", "color": "#cc6ab5"}, "cosmetic8567": {"text": "걸플갤", "color": "#cc6ab5"}, "cost7344": {"text": "걸플갤", "color": "#cc6ab5"}, "cotton0877": {"text": "걸플갤", "color": "#cc6ab5"}, "count7417": {"text": "걸플갤", "color": "#cc6ab5"}, "cowboy9150": {"text": "걸플갤", "color": "#cc6ab5"}, "crane6271": {"text": "걸플갤", "color": "#cc6ab5"}, "crazy2833": {"text": "걸플갤", "color": "#cc6ab5"}, "creature5804": {"text": "걸플갤", "color": "#cc6ab5"}, "crime1145": {"text": "걸플갤", "color": "#cc6ab5"}, "criminal2447": {"text": "걸플갤", "color": "#cc6ab5"}, "crisp3475": {"text": "걸플갤", "color": "#cc6ab5"}, "critic2469": {"text": "걸플갤", "color": "#cc6ab5"}, "cross2272": {"text": "걸플갤", "color": "#cc6ab5"}, "crow5822": {"text": "걸플갤", "color": "#cc6ab5"}, "crowd3986": {"text": "걸플갤", "color": "#cc6ab5"}, "crucial7770": {"text": "걸플갤", "color": "#cc6ab5"}, "crush5564": {"text": "걸플갤", "color": "#cc6ab5"}, "cucumber1019": {"text": "걸플갤", "color": "#cc6ab5"}, "curl0438": {"text": "걸플갤", "color": "#cc6ab5"}, "dakbob": {"text": "걸플갤", "color": "#cc6ab5"}, "dalfong2": {"text": "걸플갤", "color": "#cc6ab5"}, "danger4201": {"text": "걸플갤", "color": "#cc6ab5"}, "dash8329": {"text": "걸플갤", "color": "#cc6ab5"}, "dasu22": {"text": "걸플갤", "color": "#cc6ab5"}, "database6325": {"text": "걸플갤", "color": "#cc6ab5"}, "dc0901": {"text": "걸플갤", "color": "#cc6ab5"}, "dchina602": {"text": "걸플갤", "color": "#cc6ab5"}, "ddraomnevcwm": {"text": "걸플갤", "color": "#cc6ab5"}, "ddssaa12345": {"text": "걸플갤", "color": "#cc6ab5"}, "deb8d428f3rj": {"text": "걸플갤", "color": "#cc6ab5"}, "decade1953": {"text": "걸플갤", "color": "#cc6ab5"}, "deceive6918": {"text": "걸플갤", "color": "#cc6ab5"}, "decided2315": {"text": "걸플갤", "color": "#cc6ab5"}, "declare6817": {"text": "걸플갤", "color": "#cc6ab5"}, "deedee333": {"text": "걸플갤", "color": "#cc6ab5"}, "deeply9659": {"text": "걸플갤", "color": "#cc6ab5"}, "define4830": {"text": "걸플갤", "color": "#cc6ab5"}, "degrade3078": {"text": "걸플갤", "color": "#cc6ab5"}, "degree0718": {"text": "걸플갤", "color": "#cc6ab5"}, "derive3797": {"text": "걸플갤", "color": "#cc6ab5"}, "descend2584": {"text": "걸플갤", "color": "#cc6ab5"}, "desk3703": {"text": "걸플갤", "color": "#cc6ab5"}, "detail8294": {"text": "걸플갤", "color": "#cc6ab5"}, "devil14162": {"text": "걸플갤", "color": "#cc6ab5"}, "dfr68jqgvh6e": {"text": "걸플갤", "color": "#cc6ab5"}, "dh97js89yj99": {"text": "걸플갤", "color": "#cc6ab5"}, "diamond0090": {"text": "걸플갤", "color": "#cc6ab5"}, "digest1852": {"text": "걸플갤", "color": "#cc6ab5"}, "dimn22": {"text": "걸플갤", "color": "#cc6ab5"}, "diplomat9849": {"text": "걸플갤", "color": "#cc6ab5"}, "directly6250": {"text": "걸플갤", "color": "#cc6ab5"}, "discover0004": {"text": "걸플갤", "color": "#cc6ab5"}, "disorder3712": {"text": "걸플갤", "color": "#cc6ab5"}, "divide4100": {"text": "걸플갤", "color": "#cc6ab5"}, "diving4663": {"text": "걸플갤", "color": "#cc6ab5"}, "dkfkaltm1": {"text": "걸플갤", "color": "#cc6ab5"}, "dolphin7756": {"text": "걸플갤", "color": "#cc6ab5"}, "donation4824": {"text": "걸플갤", "color": "#cc6ab5"}, "dongidel20": {"text": "걸플갤", "color": "#cc6ab5"}, "dose3397": {"text": "걸플갤", "color": "#cc6ab5"}, "double9605": {"text": "걸플갤", "color": "#cc6ab5"}, "downside8302": {"text": "걸플갤", "color": "#cc6ab5"}, "dradragon": {"text": "걸플갤", "color": "#cc6ab5"}, "drag1001": {"text": "걸플갤", "color": "#cc6ab5"}, "dress2724": {"text": "걸플갤", "color": "#cc6ab5"}, "drug8722": {"text": "걸플갤", "color": "#cc6ab5"}, "dtd105105": {"text": "걸플갤", "color": "#cc6ab5"}, "dwell3100": {"text": "걸플갤", "color": "#cc6ab5"}, "e1elkg0f9twe": {"text": "걸플갤", "color": "#cc6ab5"}, "each4765": {"text": "걸플갤", "color": "#cc6ab5"}, "earring0486": {"text": "걸플갤", "color": "#cc6ab5"}, "ease8688": {"text": "걸플갤", "color": "#cc6ab5"}, "eastern1670": {"text": "걸플갤", "color": "#cc6ab5"}, "easy2550": {"text": "걸플갤", "color": "#cc6ab5"}, "economic6525": {"text": "걸플갤", "color": "#cc6ab5"}, "economy4628": {"text": "걸플갤", "color": "#cc6ab5"}, "effect5934": {"text": "걸플갤", "color": "#cc6ab5"}, "eggkmc3": {"text": "걸플갤", "color": "#cc6ab5"}, "eighth3329": {"text": "걸플갤", "color": "#cc6ab5"}, "ej04579983": {"text": "걸플갤", "color": "#cc6ab5"}, "ejtidl2": {"text": "걸플갤", "color": "#cc6ab5"}, "elect0109": {"text": "걸플갤", "color": "#cc6ab5"}, "else9062": {"text": "걸플갤", "color": "#cc6ab5"}, "eltlqlalfqjsgh": {"text": "걸플갤", "color": "#cc6ab5"}, "email7914": {"text": "걸플갤", "color": "#cc6ab5"}, "emerge6949": {"text": "걸플갤", "color": "#cc6ab5"}, "enclose8569": {"text": "걸플갤", "color": "#cc6ab5"}, "enemy3346": {"text": "걸플갤", "color": "#cc6ab5"}, "enf1mjy8mybh": {"text": "걸플갤", "color": "#cc6ab5"}, "engage7379": {"text": "걸플갤", "color": "#cc6ab5"}, "enhance0489": {"text": "걸플갤", "color": "#cc6ab5"}, "enu17lfnkpc9": {"text": "걸플갤", "color": "#cc6ab5"}, "eridu3": {"text": "걸플갤", "color": "#cc6ab5"}, "erker0406": {"text": "걸플갤", "color": "#cc6ab5"}, "error7534": {"text": "걸플갤", "color": "#cc6ab5"}, "espree": {"text": "걸플갤", "color": "#cc6ab5"}, "evening4157": {"text": "걸플갤", "color": "#cc6ab5"}, "exceed5178": {"text": "걸플갤", "color": "#cc6ab5"}, "excite0243": {"text": "걸플갤", "color": "#cc6ab5"}, "excite0930": {"text": "걸플갤", "color": "#cc6ab5"}, "explode9670": {"text": "걸플갤", "color": "#cc6ab5"}, "export1764": {"text": "걸플갤", "color": "#cc6ab5"}, "extinct1254": {"text": "걸플갤", "color": "#cc6ab5"}, "extra6523": {"text": "걸플갤", "color": "#cc6ab5"}, "extract1811": {"text": "걸플갤", "color": "#cc6ab5"}, "f7qgvy7jghpf": {"text": "걸플갤", "color": "#cc6ab5"}, "fail3131": {"text": "걸플갤", "color": "#cc6ab5"}, "fair3113": {"text": "걸플갤", "color": "#cc6ab5"}, "fairy7381": {"text": "걸플갤", "color": "#cc6ab5"}, "faithful8720": {"text": "걸플갤", "color": "#cc6ab5"}, "farishta9416": {"text": "걸플갤", "color": "#cc6ab5"}, "fellow1992": {"text": "걸플갤", "color": "#cc6ab5"}, "female8927": {"text": "걸플갤", "color": "#cc6ab5"}, "fhezv78k5cdr": {"text": "걸플갤", "color": "#cc6ab5"}, "fierce3828": {"text": "걸플갤", "color": "#cc6ab5"}, "fifth0282": {"text": "걸플갤", "color": "#cc6ab5"}, "final9128": {"text": "걸플갤", "color": "#cc6ab5"}, "finger0424": {"text": "걸플갤", "color": "#cc6ab5"}, "fire8133": {"text": "걸플갤", "color": "#cc6ab5"}, "fitness0195": {"text": "걸플갤", "color": "#cc6ab5"}, "fixed5604": {"text": "걸플갤", "color": "#cc6ab5"}, "flag4426": {"text": "걸플갤", "color": "#cc6ab5"}, "flare2020": {"text": "걸플갤", "color": "#cc6ab5"}, "flash0697": {"text": "걸플갤", "color": "#cc6ab5"}, "flash1408": {"text": "걸플갤", "color": "#cc6ab5"}, "flash2931": {"text": "걸플갤", "color": "#cc6ab5"}, "flexible5881": {"text": "걸플갤", "color": "#cc6ab5"}, "flush8324": {"text": "걸플갤", "color": "#cc6ab5"}, "fnl3bv5htwjh": {"text": "걸플갤", "color": "#cc6ab5"}, "food4587": {"text": "걸플갤", "color": "#cc6ab5"}, "forbid0600": {"text": "걸플갤", "color": "#cc6ab5"}, "forbid8238": {"text": "걸플갤", "color": "#cc6ab5"}, "foreign8020": {"text": "걸플갤", "color": "#cc6ab5"}, "fraction5014": {"text": "걸플갤", "color": "#cc6ab5"}, "frame9193": {"text": "걸플갤", "color": "#cc6ab5"}, "freedom1055": {"text": "걸플갤", "color": "#cc6ab5"}, "freezing4581": {"text": "걸플갤", "color": "#cc6ab5"}, "french5060": {"text": "걸플갤", "color": "#cc6ab5"}, "fright3053": {"text": "걸플갤", "color": "#cc6ab5"}, "frog7319": {"text": "걸플갤", "color": "#cc6ab5"}, "fromise": {"text": "걸플갤", "color": "#cc6ab5"}, "fuckyounigger": {"text": "걸플갤", "color": "#cc6ab5"}, "fully2276": {"text": "걸플갤", "color": "#cc6ab5"}, "funny7840": {"text": "걸플갤", "color": "#cc6ab5"}, "future4926": {"text": "걸플갤", "color": "#cc6ab5"}, "galaxy6411": {"text": "걸플갤", "color": "#cc6ab5"}, "galveston": {"text": "걸플갤", "color": "#cc6ab5"}, "garden9567": {"text": "걸플갤", "color": "#cc6ab5"}, "gaze0607": {"text": "걸플갤", "color": "#cc6ab5"}, "gear2904": {"text": "걸플갤", "color": "#cc6ab5"}, "genuine4461": {"text": "걸플갤", "color": "#cc6ab5"}, "germany2890": {"text": "걸플갤", "color": "#cc6ab5"}, "ggplay20": {"text": "걸플갤", "color": "#cc6ab5"}, "ghdyd214": {"text": "걸플갤", "color": "#cc6ab5"}, "gift2223": {"text": "걸플갤", "color": "#cc6ab5"}, "gkffpffndi99": {"text": "걸플갤", "color": "#cc6ab5"}, "gkh1402": {"text": "걸플갤", "color": "#cc6ab5"}, "glad2933": {"text": "걸플갤", "color": "#cc6ab5"}, "glass4959": {"text": "걸플갤", "color": "#cc6ab5"}, "glue7381": {"text": "걸플갤", "color": "#cc6ab5"}, "goat2": {"text": "걸플갤", "color": "#cc6ab5"}, "gointj": {"text": "걸플갤", "color": "#cc6ab5"}, "good8046": {"text": "걸플갤", "color": "#cc6ab5"}, "gossip3172": {"text": "걸플갤", "color": "#cc6ab5"}, "gqq0s7afuoxp": {"text": "걸플갤", "color": "#cc6ab5"}, "grain2862": {"text": "걸플갤", "color": "#cc6ab5"}, "grammar1989": {"text": "걸플갤", "color": "#cc6ab5"}, "grandkross79": {"text": "걸플갤", "color": "#cc6ab5"}, "grandson9684": {"text": "걸플갤", "color": "#cc6ab5"}, "grant6260": {"text": "걸플갤", "color": "#cc6ab5"}, "grape4065": {"text": "걸플갤", "color": "#cc6ab5"}, "graphic7326": {"text": "걸플갤", "color": "#cc6ab5"}, "graze9436": {"text": "걸플갤", "color": "#cc6ab5"}, "greennose": {"text": "걸플갤", "color": "#cc6ab5"}, "grief7263": {"text": "걸플갤", "color": "#cc6ab5"}, "ground3105": {"text": "걸플갤", "color": "#cc6ab5"}, "group4143": {"text": "걸플갤", "color": "#cc6ab5"}, "group8707": {"text": "걸플갤", "color": "#cc6ab5"}, "gto8109": {"text": "걸플갤", "color": "#cc6ab5"}, "guest8753": {"text": "걸플갤", "color": "#cc6ab5"}, "guide6687": {"text": "걸플갤", "color": "#cc6ab5"}, "guilty5623": {"text": "걸플갤", "color": "#cc6ab5"}, "guilty8750": {"text": "걸플갤", "color": "#cc6ab5"}, "guitar1216": {"text": "걸플갤", "color": "#cc6ab5"}, "gyaaaaaaaa": {"text": "걸플갤", "color": "#cc6ab5"}, "gyeonun": {"text": "걸플갤", "color": "#cc6ab5"}, "habit5336": {"text": "걸플갤", "color": "#cc6ab5"}, "hachki123": {"text": "걸플갤", "color": "#cc6ab5"}, "hammer7043": {"text": "걸플갤", "color": "#cc6ab5"}, "hammergod": {"text": "걸플갤", "color": "#cc6ab5"}, "handicap0009": {"text": "걸플갤", "color": "#cc6ab5"}, "hang8400": {"text": "걸플갤", "color": "#cc6ab5"}, "happen7148": {"text": "걸플갤", "color": "#cc6ab5"}, "happyday0906": {"text": "걸플갤", "color": "#cc6ab5"}, "harm0546": {"text": "걸플갤", "color": "#cc6ab5"}, "harmful9816": {"text": "걸플갤", "color": "#cc6ab5"}, "harsh6900": {"text": "걸플갤", "color": "#cc6ab5"}, "harvest1681": {"text": "걸플갤", "color": "#cc6ab5"}, "haste1289": {"text": "걸플갤", "color": "#cc6ab5"}, "haste9469": {"text": "걸플갤", "color": "#cc6ab5"}, "hatch1225": {"text": "걸플갤", "color": "#cc6ab5"}, "hatesome": {"text": "걸플갤", "color": "#cc6ab5"}, "hazard2296": {"text": "걸플갤", "color": "#cc6ab5"}, "headline0533": {"text": "걸플갤", "color": "#cc6ab5"}, "heir7968": {"text": "걸플갤", "color": "#cc6ab5"}, "helenab6": {"text": "걸플갤", "color": "#cc6ab5"}, "hellbent": {"text": "걸플갤", "color": "#cc6ab5"}, "hello0511": {"text": "걸플갤", "color": "#cc6ab5"}, "hesitate4325": {"text": "걸플갤", "color": "#cc6ab5"}, "hg4562": {"text": "걸플갤", "color": "#cc6ab5"}, "hgbc197qg382": {"text": "걸플갤", "color": "#cc6ab5"}, "hill3015": {"text": "걸플갤", "color": "#cc6ab5"}, "hire6006": {"text": "걸플갤", "color": "#cc6ab5"}, "homemade0036": {"text": "걸플갤", "color": "#cc6ab5"}, "homeroom9709": {"text": "걸플갤", "color": "#cc6ab5"}, "hometown4692": {"text": "걸플갤", "color": "#cc6ab5"}, "honored1186": {"text": "걸플갤", "color": "#cc6ab5"}, "hope5745": {"text": "걸플갤", "color": "#cc6ab5"}, "hoshea12": {"text": "걸플갤", "color": "#cc6ab5"}, "humid0926": {"text": "걸플갤", "color": "#cc6ab5"}, "humorous1505": {"text": "걸플갤", "color": "#cc6ab5"}, "hungfan4": {"text": "걸플갤", "color": "#cc6ab5"}, "hurry3533": {"text": "걸플갤", "color": "#cc6ab5"}, "i78n2pnvaj1i": {"text": "걸플갤", "color": "#cc6ab5"}, "ic81b0sk7dx8": {"text": "걸플갤", "color": "#cc6ab5"}, "iceco": {"text": "걸플갤", "color": "#cc6ab5"}, "identity4175": {"text": "걸플갤", "color": "#cc6ab5"}, "improve3745": {"text": "걸플갤", "color": "#cc6ab5"}, "imsotireds": {"text": "걸플갤", "color": "#cc6ab5"}, "indark9": {"text": "걸플갤", "color": "#cc6ab5"}, "informal2535": {"text": "걸플갤", "color": "#cc6ab5"}, "inject5467": {"text": "걸플갤", "color": "#cc6ab5"}, "injure6683": {"text": "걸플갤", "color": "#cc6ab5"}, "inning0476": {"text": "걸플갤", "color": "#cc6ab5"}, "inning6502": {"text": "걸플갤", "color": "#cc6ab5"}, "inquire8697": {"text": "걸플갤", "color": "#cc6ab5"}, "insight1801": {"text": "걸플갤", "color": "#cc6ab5"}, "inspect0332": {"text": "걸플갤", "color": "#cc6ab5"}, "instance0190": {"text": "걸플갤", "color": "#cc6ab5"}, "instead9537": {"text": "걸플갤", "color": "#cc6ab5"}, "instinct9134": {"text": "걸플갤", "color": "#cc6ab5"}, "intense0758": {"text": "걸플갤", "color": "#cc6ab5"}, "intrigue1049": {"text": "걸플갤", "color": "#cc6ab5"}, "invade5205": {"text": "걸플갤", "color": "#cc6ab5"}, "inventor9574": {"text": "걸플갤", "color": "#cc6ab5"}, "invest9641": {"text": "걸플갤", "color": "#cc6ab5"}, "involve6599": {"text": "걸플갤", "color": "#cc6ab5"}, "iron1788": {"text": "걸플갤", "color": "#cc6ab5"}, "iron8793": {"text": "걸플갤", "color": "#cc6ab5"}, "item6704": {"text": "걸플갤", "color": "#cc6ab5"}, "iziziz12": {"text": "걸플갤", "color": "#cc6ab5"}, "j7jzw2qktcg6": {"text": "걸플갤", "color": "#cc6ab5"}, "janeinjuly": {"text": "걸플갤", "color": "#cc6ab5"}, "janggook3": {"text": "걸플갤", "color": "#cc6ab5"}, "japanese3730": {"text": "걸플갤", "color": "#cc6ab5"}, "jason9463": {"text": "걸플갤", "color": "#cc6ab5"}, "jc3449": {"text": "걸플갤", "color": "#cc6ab5"}, "jesusss": {"text": "걸플갤", "color": "#cc6ab5"}, "jhun009": {"text": "걸플갤", "color": "#cc6ab5"}, "jichi": {"text": "걸플갤", "color": "#cc6ab5"}, "jin331f": {"text": "걸플갤", "color": "#cc6ab5"}, "jodongu05": {"text": "걸플갤", "color": "#cc6ab5"}, "joongdingstockking9": {"text": "걸플갤", "color": "#cc6ab5"}, "journal3891": {"text": "걸플갤", "color": "#cc6ab5"}, "jungjoon0001": {"text": "걸플갤", "color": "#cc6ab5"}, "jupiter7129": {"text": "걸플갤", "color": "#cc6ab5"}, "justify2076": {"text": "걸플갤", "color": "#cc6ab5"}, "juxta50": {"text": "걸플갤", "color": "#cc6ab5"}, "kakarin4": {"text": "걸플갤", "color": "#cc6ab5"}, "kamilaona": {"text": "걸플갤", "color": "#cc6ab5"}, "kick7244": {"text": "걸플갤", "color": "#cc6ab5"}, "kick9137": {"text": "걸플갤", "color": "#cc6ab5"}, "kikiki13579": {"text": "걸플갤", "color": "#cc6ab5"}, "killmoon0509": {"text": "걸플갤", "color": "#cc6ab5"}, "kimjunseo12": {"text": "걸플갤", "color": "#cc6ab5"}, "kimnakyoung": {"text": "걸플갤", "color": "#cc6ab5"}, "kind1926": {"text": "걸플갤", "color": "#cc6ab5"}, "kindness7389": {"text": "걸플갤", "color": "#cc6ab5"}, "kinginjik": {"text": "걸플갤", "color": "#cc6ab5"}, "kingtta747": {"text": "걸플갤", "color": "#cc6ab5"}, "kitchen9911": {"text": "걸플갤", "color": "#cc6ab5"}, "kjsbond3": {"text": "걸플갤", "color": "#cc6ab5"}, "kkkiiioos": {"text": "걸플갤", "color": "#cc6ab5"}, "knot4380": {"text": "걸플갤", "color": "#cc6ab5"}, "kshcdy": {"text": "걸플갤", "color": "#cc6ab5"}, "ksz4mq6": {"text": "걸플갤", "color": "#cc6ab5"}, "kurupat44": {"text": "걸플갤", "color": "#cc6ab5"}, "kwonclub0814": {"text": "걸플갤", "color": "#cc6ab5"}, "kyk3885": {"text": "걸플갤", "color": "#cc6ab5"}, "l4yke4doybl1": {"text": "걸플갤", "color": "#cc6ab5"}, "lake3248": {"text": "걸플갤", "color": "#cc6ab5"}, "lake8884": {"text": "걸플갤", "color": "#cc6ab5"}, "late6500": {"text": "걸플갤", "color": "#cc6ab5"}, "lawyer2829": {"text": "걸플갤", "color": "#cc6ab5"}, "lead9128": {"text": "걸플갤", "color": "#cc6ab5"}, "leaf4494": {"text": "걸플갤", "color": "#cc6ab5"}, "lecture0690": {"text": "걸플갤", "color": "#cc6ab5"}, "lee1003": {"text": "걸플갤", "color": "#cc6ab5"}, "leesy9204": {"text": "걸플갤", "color": "#cc6ab5"}, "legal8106": {"text": "걸플갤", "color": "#cc6ab5"}, "leisure4349": {"text": "걸플갤", "color": "#cc6ab5"}, "length3958": {"text": "걸플갤", "color": "#cc6ab5"}, "lens0939": {"text": "걸플갤", "color": "#cc6ab5"}, "lens8738": {"text": "걸플갤", "color": "#cc6ab5"}, "liar5385": {"text": "걸플갤", "color": "#cc6ab5"}, "liberty2413": {"text": "걸플갤", "color": "#cc6ab5"}, "light8959": {"text": "걸플갤", "color": "#cc6ab5"}, "limman92": {"text": "걸플갤", "color": "#cc6ab5"}, "limman98": {"text": "걸플갤", "color": "#cc6ab5"}, "link5139": {"text": "걸플갤", "color": "#cc6ab5"}, "list2233": {"text": "걸플갤", "color": "#cc6ab5"}, "list5316": {"text": "걸플갤", "color": "#cc6ab5"}, "listener3009": {"text": "걸플갤", "color": "#cc6ab5"}, "living5239": {"text": "걸플갤", "color": "#cc6ab5"}, "lllllllllll1llll": {"text": "걸플갤", "color": "#cc6ab5"}, "locate2797": {"text": "걸플갤", "color": "#cc6ab5"}, "longsword0716": {"text": "걸플갤", "color": "#cc6ab5"}, "loose7924": {"text": "걸플갤", "color": "#cc6ab5"}, "lost1283": {"text": "걸플갤", "color": "#cc6ab5"}, "lu3246": {"text": "걸플갤", "color": "#cc6ab5"}, "lunch4070": {"text": "걸플갤", "color": "#cc6ab5"}, "luvjw": {"text": "걸플갤", "color": "#cc6ab5"}, "madocals1234": {"text": "걸플갤", "color": "#cc6ab5"}, "majordowntown": {"text": "걸플갤", "color": "#cc6ab5"}, "mama16794": {"text": "걸플갤", "color": "#cc6ab5"}, "market9820": {"text": "걸플갤", "color": "#cc6ab5"}, "marriage3091": {"text": "걸플갤", "color": "#cc6ab5"}, "mars3265": {"text": "걸플갤", "color": "#cc6ab5"}, "mask5759": {"text": "걸플갤", "color": "#cc6ab5"}, "mass3316": {"text": "걸플갤", "color": "#cc6ab5"}, "match3546": {"text": "걸플갤", "color": "#cc6ab5"}, "max0152": {"text": "걸플갤", "color": "#cc6ab5"}, "mcdonaldsbigmac": {"text": "걸플갤", "color": "#cc6ab5"}, "mdcinsde": {"text": "걸플갤", "color": "#cc6ab5"}, "meatball9049": {"text": "걸플갤", "color": "#cc6ab5"}, "member5061": {"text": "걸플갤", "color": "#cc6ab5"}, "memorial7413": {"text": "걸플갤", "color": "#cc6ab5"}, "mental6221": {"text": "걸플갤", "color": "#cc6ab5"}, "mere5083": {"text": "걸플갤", "color": "#cc6ab5"}, "migrate7058": {"text": "걸플갤", "color": "#cc6ab5"}, "milk2837": {"text": "걸플갤", "color": "#cc6ab5"}, "mind9381": {"text": "걸플갤", "color": "#cc6ab5"}, "mine8475": {"text": "걸플갤", "color": "#cc6ab5"}, "minguri123": {"text": "걸플갤", "color": "#cc6ab5"}, "minju2001": {"text": "걸플갤", "color": "#cc6ab5"}, "mission3989": {"text": "걸플갤", "color": "#cc6ab5"}, "mock9146": {"text": "걸플갤", "color": "#cc6ab5"}, "monday1375": {"text": "걸플갤", "color": "#cc6ab5"}, "moon7217": {"text": "걸플갤", "color": "#cc6ab5"}, "moringatree": {"text": "걸플갤", "color": "#cc6ab5"}, "mouth1254": {"text": "걸플갤", "color": "#cc6ab5"}, "mqabojvlsg47": {"text": "걸플갤", "color": "#cc6ab5"}, "much5740": {"text": "걸플갤", "color": "#cc6ab5"}, "muddy7032": {"text": "걸플갤", "color": "#cc6ab5"}, "music3408": {"text": "걸플갤", "color": "#cc6ab5"}, "mutual0862": {"text": "걸플갤", "color": "#cc6ab5"}, "mv3456": {"text": "걸플갤", "color": "#cc6ab5"}, "mvcxuqn9kll4": {"text": "걸플갤", "color": "#cc6ab5"}, "myaostagram": {"text": "걸플갤", "color": "#cc6ab5"}, "myself8907": {"text": "걸플갤", "color": "#cc6ab5"}, "n1cpd6hawue9": {"text": "걸플갤", "color": "#cc6ab5"}, "narrate2410": {"text": "걸플갤", "color": "#cc6ab5"}, "native8944": {"text": "걸플갤", "color": "#cc6ab5"}, "navy8925": {"text": "걸플갤", "color": "#cc6ab5"}, "nbhh46em1aye": {"text": "걸플갤", "color": "#cc6ab5"}, "neighbor2754": {"text": "걸플갤", "color": "#cc6ab5"}, "new35": {"text": "걸플갤", "color": "#cc6ab5"}, "new37": {"text": "걸플갤", "color": "#cc6ab5"}, "newborn8157": {"text": "걸플갤", "color": "#cc6ab5"}, "news0673": {"text": "걸플갤", "color": "#cc6ab5"}, "next6660": {"text": "걸플갤", "color": "#cc6ab5"}, "niece3154": {"text": "걸플갤", "color": "#cc6ab5"}, "niece9860": {"text": "걸플갤", "color": "#cc6ab5"}, "night9763": {"text": "걸플갤", "color": "#cc6ab5"}, "nirvanamania": {"text": "걸플갤", "color": "#cc6ab5"}, "njeo22": {"text": "걸플갤", "color": "#cc6ab5"}, "nobody6925": {"text": "걸플갤", "color": "#cc6ab5"}, "noisy8909": {"text": "걸플갤", "color": "#cc6ab5"}, "nokyong": {"text": "걸플갤", "color": "#cc6ab5"}, "nonoca": {"text": "걸플갤", "color": "#cc6ab5"}, "normally4289": {"text": "걸플갤", "color": "#cc6ab5"}, "nowadays1009": {"text": "걸플갤", "color": "#cc6ab5"}, "np4y41pczlr5": {"text": "걸플갤", "color": "#cc6ab5"}, "numeral2223": {"text": "걸플갤", "color": "#cc6ab5"}, "ohohjang": {"text": "걸플갤", "color": "#cc6ab5"}, "omomgod": {"text": "걸플갤", "color": "#cc6ab5"}, "onion3690": {"text": "걸플갤", "color": "#cc6ab5"}, "ons999": {"text": "걸플갤", "color": "#cc6ab5"}, "onto6696": {"text": "걸플갤", "color": "#cc6ab5"}, "ootid2": {"text": "걸플갤", "color": "#cc6ab5"}, "organize6701": {"text": "걸플갤", "color": "#cc6ab5"}, "original3755": {"text": "걸플갤", "color": "#cc6ab5"}, "ours0813": {"text": "걸플갤", "color": "#cc6ab5"}, "outdoor9388": {"text": "걸플갤", "color": "#cc6ab5"}, "outgoing6094": {"text": "걸플갤", "color": "#cc6ab5"}, "outside9536": {"text": "걸플갤", "color": "#cc6ab5"}, "oval1438": {"text": "걸플갤", "color": "#cc6ab5"}, "overhead6682": {"text": "걸플갤", "color": "#cc6ab5"}, "p1altwptqx0y": {"text": "걸플갤", "color": "#cc6ab5"}, "p6238ckpdl6j": {"text": "걸플갤", "color": "#cc6ab5"}, "pack2441": {"text": "걸플갤", "color": "#cc6ab5"}, "package1943": {"text": "걸플갤", "color": "#cc6ab5"}, "panda1092": {"text": "걸플갤", "color": "#cc6ab5"}, "panda9566": {"text": "걸플갤", "color": "#cc6ab5"}, "paper1964": {"text": "걸플갤", "color": "#cc6ab5"}, "park21025": {"text": "걸플갤", "color": "#cc6ab5"}, "parking1986": {"text": "걸플갤", "color": "#cc6ab5"}, "passion8314": {"text": "걸플갤", "color": "#cc6ab5"}, "paste6262": {"text": "걸플갤", "color": "#cc6ab5"}, "patent8401": {"text": "걸플갤", "color": "#cc6ab5"}, "pathofoner": {"text": "걸플갤", "color": "#cc6ab5"}, "patrol1761": {"text": "걸플갤", "color": "#cc6ab5"}, "pb4e7uz09p79": {"text": "걸플갤", "color": "#cc6ab5"}, "peasant1082": {"text": "걸플갤", "color": "#cc6ab5"}, "persist1103": {"text": "걸플갤", "color": "#cc6ab5"}, "pharmacy2337": {"text": "걸플갤", "color": "#cc6ab5"}, "pharmacy5119": {"text": "걸플갤", "color": "#cc6ab5"}, "phone2804": {"text": "걸플갤", "color": "#cc6ab5"}, "photo1084": {"text": "걸플갤", "color": "#cc6ab5"}, "pill1139": {"text": "걸플갤", "color": "#cc6ab5"}, "pillow7819": {"text": "걸플갤", "color": "#cc6ab5"}, "pink7072": {"text": "걸플갤", "color": "#cc6ab5"}, "pioneer3044": {"text": "걸플갤", "color": "#cc6ab5"}, "piracy1581": {"text": "걸플갤", "color": "#cc6ab5"}, "pizza5250": {"text": "걸플갤", "color": "#cc6ab5"}, "pizza7169": {"text": "걸플갤", "color": "#cc6ab5"}, "place2979": {"text": "걸플갤", "color": "#cc6ab5"}, "plain4001": {"text": "걸플갤", "color": "#cc6ab5"}, "plant6660": {"text": "걸플갤", "color": "#cc6ab5"}, "pleasure6295": {"text": "걸플갤", "color": "#cc6ab5"}, "plot8382": {"text": "걸플갤", "color": "#cc6ab5"}, "plploop": {"text": "걸플갤", "color": "#cc6ab5"}, "pointed0690": {"text": "걸플갤", "color": "#cc6ab5"}, "poiuypoiuypoiuy": {"text": "걸플갤", "color": "#cc6ab5"}, "pokapoka2023": {"text": "걸플갤", "color": "#cc6ab5"}, "poll1369": {"text": "걸플갤", "color": "#cc6ab5"}, "pollute2514": {"text": "걸플갤", "color": "#cc6ab5"}, "pope2453": {"text": "걸플갤", "color": "#cc6ab5"}, "pope8779": {"text": "걸플갤", "color": "#cc6ab5"}, "poppop33": {"text": "걸플갤", "color": "#cc6ab5"}, "popular4780": {"text": "걸플갤", "color": "#cc6ab5"}, "poqwman": {"text": "걸플갤", "color": "#cc6ab5"}, "portable9658": {"text": "걸플갤", "color": "#cc6ab5"}, "pose8840": {"text": "걸플갤", "color": "#cc6ab5"}, "poster7162": {"text": "걸플갤", "color": "#cc6ab5"}, "poster8700": {"text": "걸플갤", "color": "#cc6ab5"}, "potato3679": {"text": "걸플갤", "color": "#cc6ab5"}, "prefer7673": {"text": "걸플갤", "color": "#cc6ab5"}, "preserve6029": {"text": "걸플갤", "color": "#cc6ab5"}, "pretty9828": {"text": "걸플갤", "color": "#cc6ab5"}, "princess1139": {"text": "걸플갤", "color": "#cc6ab5"}, "princess5002": {"text": "걸플갤", "color": "#cc6ab5"}, "print6683": {"text": "걸플갤", "color": "#cc6ab5"}, "prior0255": {"text": "걸플갤", "color": "#cc6ab5"}, "prior5394": {"text": "걸플갤", "color": "#cc6ab5"}, "progress7008": {"text": "걸플갤", "color": "#cc6ab5"}, "project5940": {"text": "걸플갤", "color": "#cc6ab5"}, "promise2270": {"text": "걸플갤", "color": "#cc6ab5"}, "prose4908": {"text": "걸플갤", "color": "#cc6ab5"}, "protein2586": {"text": "걸플갤", "color": "#cc6ab5"}, "proverb5862": {"text": "걸플갤", "color": "#cc6ab5"}, "psiloveyeah": {"text": "걸플갤", "color": "#cc6ab5"}, "ptttt": {"text": "걸플갤", "color": "#cc6ab5"}, "pulgcv6a6wxt": {"text": "걸플갤", "color": "#cc6ab5"}, "pull3342": {"text": "걸플갤", "color": "#cc6ab5"}, "pull9220": {"text": "걸플갤", "color": "#cc6ab5"}, "pump1498": {"text": "걸플갤", "color": "#cc6ab5"}, "punish4308": {"text": "걸플갤", "color": "#cc6ab5"}, "q8624224": {"text": "걸플갤", "color": "#cc6ab5"}, "qkakfl4": {"text": "걸플갤", "color": "#cc6ab5"}, "qlsgh100987": {"text": "걸플갤", "color": "#cc6ab5"}, "qndld1234": {"text": "걸플갤", "color": "#cc6ab5"}, "qpzjawnsldj": {"text": "걸플갤", "color": "#cc6ab5"}, "quantity7808": {"text": "걸플갤", "color": "#cc6ab5"}, "qudwl": {"text": "걸플갤", "color": "#cc6ab5"}, "qufdldjssl96": {"text": "걸플갤", "color": "#cc6ab5"}, "qwerqwer1584": {"text": "걸플갤", "color": "#cc6ab5"}, "qwerty963500": {"text": "걸플갤", "color": "#cc6ab5"}, "r5zr7ughg9ek": {"text": "걸플갤", "color": "#cc6ab5"}, "rain2978": {"text": "걸플갤", "color": "#cc6ab5"}, "raincoat3839": {"text": "걸플갤", "color": "#cc6ab5"}, "raincoat6802": {"text": "걸플갤", "color": "#cc6ab5"}, "rainy2203": {"text": "걸플갤", "color": "#cc6ab5"}, "rally9180": {"text": "걸플갤", "color": "#cc6ab5"}, "ramram224": {"text": "걸플갤", "color": "#cc6ab5"}, "rbgjzyo": {"text": "걸플갤", "color": "#cc6ab5"}, "reach0294": {"text": "걸플갤", "color": "#cc6ab5"}, "ready2084": {"text": "걸플갤", "color": "#cc6ab5"}, "real2302": {"text": "걸플갤", "color": "#cc6ab5"}, "realanaysis": {"text": "걸플갤", "color": "#cc6ab5"}, "realgoodzz": {"text": "걸플갤", "color": "#cc6ab5"}, "realize7531": {"text": "걸플갤", "color": "#cc6ab5"}, "rear4675": {"text": "걸플갤", "color": "#cc6ab5"}, "receipt6225": {"text": "걸플갤", "color": "#cc6ab5"}, "recently9226": {"text": "걸플갤", "color": "#cc6ab5"}, "refine8494": {"text": "걸플갤", "color": "#cc6ab5"}, "rememberfireworks": {"text": "걸플갤", "color": "#cc6ab5"}, "remote5622": {"text": "걸플갤", "color": "#cc6ab5"}, "rent2314": {"text": "걸플갤", "color": "#cc6ab5"}, "repair3055": {"text": "걸플갤", "color": "#cc6ab5"}, "repair7741": {"text": "걸플갤", "color": "#cc6ab5"}, "replace9275": {"text": "걸플갤", "color": "#cc6ab5"}, "report5207": {"text": "걸플갤", "color": "#cc6ab5"}, "republic5926": {"text": "걸플갤", "color": "#cc6ab5"}, "reside0643": {"text": "걸플갤", "color": "#cc6ab5"}, "resign2019": {"text": "걸플갤", "color": "#cc6ab5"}, "resort8504": {"text": "걸플갤", "color": "#cc6ab5"}, "result4301": {"text": "걸플갤", "color": "#cc6ab5"}, "resume0596": {"text": "걸플갤", "color": "#cc6ab5"}, "retain4692": {"text": "걸플갤", "color": "#cc6ab5"}, "reverse01": {"text": "걸플갤", "color": "#cc6ab5"}, "reverse1992": {"text": "걸플갤", "color": "#cc6ab5"}, "revise7320": {"text": "걸플갤", "color": "#cc6ab5"}, "rhythm7696": {"text": "걸플갤", "color": "#cc6ab5"}, "richness5260": {"text": "걸플갤", "color": "#cc6ab5"}, "right1351": {"text": "걸플갤", "color": "#cc6ab5"}, "right7892": {"text": "걸플갤", "color": "#cc6ab5"}, "rndjfkfs": {"text": "걸플갤", "color": "#cc6ab5"}, "rnjsdmsql133": {"text": "걸플갤", "color": "#cc6ab5"}, "rodlftjd2": {"text": "걸플갤", "color": "#cc6ab5"}, "role2560": {"text": "걸플갤", "color": "#cc6ab5"}, "rorpin1": {"text": "걸플갤", "color": "#cc6ab5"}, "rose444444": {"text": "걸플갤", "color": "#cc6ab5"}, "rotten1317": {"text": "걸플갤", "color": "#cc6ab5"}, "royal5593": {"text": "걸플갤", "color": "#cc6ab5"}, "rqdiadem": {"text": "걸플갤", "color": "#cc6ab5"}, "rude5307": {"text": "걸플갤", "color": "#cc6ab5"}, "runny0032": {"text": "걸플갤", "color": "#cc6ab5"}, "rush2768": {"text": "걸플갤", "color": "#cc6ab5"}, "ryuddrr": {"text": "걸플갤", "color": "#cc6ab5"}, "s2yeonjun": {"text": "걸플갤", "color": "#cc6ab5"}, "satisfy3925": {"text": "걸플갤", "color": "#cc6ab5"}, "save2570": {"text": "걸플갤", "color": "#cc6ab5"}, "save7449": {"text": "걸플갤", "color": "#cc6ab5"}, "scared6019": {"text": "걸플갤", "color": "#cc6ab5"}, "scold2879": {"text": "걸플갤", "color": "#cc6ab5"}, "sdlcqnrd29xs": {"text": "걸플갤", "color": "#cc6ab5"}, "seasonal9616": {"text": "걸플갤", "color": "#cc6ab5"}, "security7377": {"text": "걸플갤", "color": "#cc6ab5"}, "seek7968": {"text": "걸플갤", "color": "#cc6ab5"}, "seize0433": {"text": "걸플갤", "color": "#cc6ab5"}, "sensible3530": {"text": "걸플갤", "color": "#cc6ab5"}, "sepido": {"text": "걸플갤", "color": "#cc6ab5"}, "serve3272": {"text": "걸플갤", "color": "#cc6ab5"}, "sesame9476": {"text": "걸플갤", "color": "#cc6ab5"}, "session3072": {"text": "걸플갤", "color": "#cc6ab5"}, "settle5365": {"text": "걸플갤", "color": "#cc6ab5"}, "shabby0968": {"text": "걸플갤", "color": "#cc6ab5"}, "shark7921": {"text": "걸플갤", "color": "#cc6ab5"}, "shell1857": {"text": "걸플갤", "color": "#cc6ab5"}, "shine3885": {"text": "걸플갤", "color": "#cc6ab5"}, "shjyyu72": {"text": "걸플갤", "color": "#cc6ab5"}, "shoe5534": {"text": "걸플갤", "color": "#cc6ab5"}, "shoot2327": {"text": "걸플갤", "color": "#cc6ab5"}, "shout0238": {"text": "걸플갤", "color": "#cc6ab5"}, "silver2786": {"text": "걸플갤", "color": "#cc6ab5"}, "simulate3139": {"text": "걸플갤", "color": "#cc6ab5"}, "singsing80": {"text": "걸플갤", "color": "#cc6ab5"}, "sistar35": {"text": "걸플갤", "color": "#cc6ab5"}, "sistar37": {"text": "걸플갤", "color": "#cc6ab5"}, "siyoon86": {"text": "걸플갤", "color": "#cc6ab5"}, "sizri72": {"text": "걸플갤", "color": "#cc6ab5"}, "ske5383": {"text": "걸플갤", "color": "#cc6ab5"}, "skinny0154": {"text": "걸플갤", "color": "#cc6ab5"}, "skirt9075": {"text": "걸플갤", "color": "#cc6ab5"}, "skqhs": {"text": "걸플갤", "color": "#cc6ab5"}, "skssk10712": {"text": "걸플갤", "color": "#cc6ab5"}, "slim9839": {"text": "걸플갤", "color": "#cc6ab5"}, "slippery7328": {"text": "걸플갤", "color": "#cc6ab5"}, "slowly1238": {"text": "걸플갤", "color": "#cc6ab5"}, "small3254": {"text": "걸플갤", "color": "#cc6ab5"}, "small3620": {"text": "걸플갤", "color": "#cc6ab5"}, "smell0583": {"text": "걸플갤", "color": "#cc6ab5"}, "smile6470": {"text": "걸플갤", "color": "#cc6ab5"}, "smiling4085": {"text": "걸플갤", "color": "#cc6ab5"}, "smoke2699": {"text": "걸플갤", "color": "#cc6ab5"}, "smoke3149": {"text": "걸플갤", "color": "#cc6ab5"}, "sn1jqkv9kxw3": {"text": "걸플갤", "color": "#cc6ab5"}, "snack3158": {"text": "걸플갤", "color": "#cc6ab5"}, "sniff3274": {"text": "걸플갤", "color": "#cc6ab5"}, "snowman1261": {"text": "걸플갤", "color": "#cc6ab5"}, "snowy8534": {"text": "걸플갤", "color": "#cc6ab5"}, "software7099": {"text": "걸플갤", "color": "#cc6ab5"}, "soil5002": {"text": "걸플갤", "color": "#cc6ab5"}, "somefire": {"text": "걸플갤", "color": "#cc6ab5"}, "song4295": {"text": "걸플갤", "color": "#cc6ab5"}, "soon1705": {"text": "걸플갤", "color": "#cc6ab5"}, "sour3289": {"text": "걸플갤", "color": "#cc6ab5"}, "spell1846": {"text": "걸플갤", "color": "#cc6ab5"}, "spell2885": {"text": "걸플갤", "color": "#cc6ab5"}, "spicy0972": {"text": "걸플갤", "color": "#cc6ab5"}, "spill1716": {"text": "걸플갤", "color": "#cc6ab5"}, "sponge2997": {"text": "걸플갤", "color": "#cc6ab5"}, "spoon3513": {"text": "걸플갤", "color": "#cc6ab5"}, "sprain7438": {"text": "걸플갤", "color": "#cc6ab5"}, "spray5288": {"text": "걸플갤", "color": "#cc6ab5"}, "spring2022": {"text": "걸플갤", "color": "#cc6ab5"}, "ssddo": {"text": "걸플갤", "color": "#cc6ab5"}, "stack7135": {"text": "걸플갤", "color": "#cc6ab5"}, "stain4399": {"text": "걸플갤", "color": "#cc6ab5"}, "stand3633": {"text": "걸플갤", "color": "#cc6ab5"}, "standard8714": {"text": "걸플갤", "color": "#cc6ab5"}, "star7014": {"text": "걸플갤", "color": "#cc6ab5"}, "state6127": {"text": "걸플갤", "color": "#cc6ab5"}, "still5324": {"text": "걸플갤", "color": "#cc6ab5"}, "stir7224": {"text": "걸플갤", "color": "#cc6ab5"}, "stomach1537": {"text": "걸플갤", "color": "#cc6ab5"}, "stop2351": {"text": "걸플갤", "color": "#cc6ab5"}, "store2907": {"text": "걸플갤", "color": "#cc6ab5"}, "stove5751": {"text": "걸플갤", "color": "#cc6ab5"}, "straight6594": {"text": "걸플갤", "color": "#cc6ab5"}, "strange89": {"text": "걸플갤", "color": "#cc6ab5"}, "strip6619": {"text": "걸플갤", "color": "#cc6ab5"}, "stripe5959": {"text": "걸플갤", "color": "#cc6ab5"}, "stroke4529": {"text": "걸플갤", "color": "#cc6ab5"}, "stroke9470": {"text": "걸플갤", "color": "#cc6ab5"}, "suburb5127": {"text": "걸플갤", "color": "#cc6ab5"}, "success9146": {"text": "걸플갤", "color": "#cc6ab5"}, "such0985": {"text": "걸플갤", "color": "#cc6ab5"}, "summer3997": {"text": "걸플갤", "color": "#cc6ab5"}, "sun1060": {"text": "걸플갤", "color": "#cc6ab5"}, "sunday1512": {"text": "걸플갤", "color": "#cc6ab5"}, "sunlight5212": {"text": "걸플갤", "color": "#cc6ab5"}, "sunset8076": {"text": "걸플갤", "color": "#cc6ab5"}, "sup2rsa1yan": {"text": "걸플갤", "color": "#cc6ab5"}, "supark78": {"text": "걸플갤", "color": "#cc6ab5"}, "superb7351": {"text": "걸플갤", "color": "#cc6ab5"}, "superior2216": {"text": "걸플갤", "color": "#cc6ab5"}, "surely9955": {"text": "걸플갤", "color": "#cc6ab5"}, "surf6618": {"text": "걸플갤", "color": "#cc6ab5"}, "swallow9922": {"text": "걸플갤", "color": "#cc6ab5"}, "swan1418": {"text": "걸플갤", "color": "#cc6ab5"}, "swimming5311": {"text": "걸플갤", "color": "#cc6ab5"}, "sybb88": {"text": "걸플갤", "color": "#cc6ab5"}, "sympathy2782": {"text": "걸플갤", "color": "#cc6ab5"}, "sympathy4115": {"text": "걸플갤", "color": "#cc6ab5"}, "symptom0855": {"text": "걸플갤", "color": "#cc6ab5"}, "syrup3331": {"text": "걸플갤", "color": "#cc6ab5"}, "table1481": {"text": "걸플갤", "color": "#cc6ab5"}, "table7253": {"text": "걸플갤", "color": "#cc6ab5"}, "tale3976": {"text": "걸플갤", "color": "#cc6ab5"}, "tale7485": {"text": "걸플갤", "color": "#cc6ab5"}, "talent8751": {"text": "걸플갤", "color": "#cc6ab5"}, "taste6139": {"text": "걸플갤", "color": "#cc6ab5"}, "tbtmtls8888": {"text": "걸플갤", "color": "#cc6ab5"}, "teaching7236": {"text": "걸플갤", "color": "#cc6ab5"}, "teaspoon1928": {"text": "걸플갤", "color": "#cc6ab5"}, "tender3176": {"text": "걸플갤", "color": "#cc6ab5"}, "tender9618": {"text": "걸플갤", "color": "#cc6ab5"}, "tense0873": {"text": "걸플갤", "color": "#cc6ab5"}, "term8452": {"text": "걸플갤", "color": "#cc6ab5"}, "test1676": {"text": "걸플갤", "color": "#cc6ab5"}, "textbook1509": {"text": "걸플갤", "color": "#cc6ab5"}, "thesand": {"text": "걸플갤", "color": "#cc6ab5"}, "thick1082": {"text": "걸플갤", "color": "#cc6ab5"}, "thick8642": {"text": "걸플갤", "color": "#cc6ab5"}, "thief0364": {"text": "걸플갤", "color": "#cc6ab5"}, "think8430": {"text": "걸플갤", "color": "#cc6ab5"}, "thousand1385": {"text": "걸플갤", "color": "#cc6ab5"}, "thsrnlqja": {"text": "걸플갤", "color": "#cc6ab5"}, "thumb2939": {"text": "걸플갤", "color": "#cc6ab5"}, "ticquat01": {"text": "걸플갤", "color": "#cc6ab5"}, "tidy8835": {"text": "걸플갤", "color": "#cc6ab5"}, "timber6485": {"text": "걸플갤", "color": "#cc6ab5"}, "tlrquf1231": {"text": "걸플갤", "color": "#cc6ab5"}, "tlwlw": {"text": "걸플갤", "color": "#cc6ab5"}, "toaster4391": {"text": "걸플갤", "color": "#cc6ab5"}, "together2391": {"text": "걸플갤", "color": "#cc6ab5"}, "togo0": {"text": "걸플갤", "color": "#cc6ab5"}, "topcurry": {"text": "걸플갤", "color": "#cc6ab5"}, "tornado2451": {"text": "걸플갤", "color": "#cc6ab5"}, "total5500": {"text": "걸플갤", "color": "#cc6ab5"}, "town1046": {"text": "걸플갤", "color": "#cc6ab5"}, "toxic6807": {"text": "걸플갤", "color": "#cc6ab5"}, "tpals1411": {"text": "걸플갤", "color": "#cc6ab5"}, "trafficlight": {"text": "걸플갤", "color": "#cc6ab5"}, "tragedy2514": {"text": "걸플갤", "color": "#cc6ab5"}, "transmit7838": {"text": "걸플갤", "color": "#cc6ab5"}, "treasure2190": {"text": "걸플갤", "color": "#cc6ab5"}, "tropical1411": {"text": "걸플갤", "color": "#cc6ab5"}, "trunk0316": {"text": "걸플갤", "color": "#cc6ab5"}, "turtle8670": {"text": "걸플갤", "color": "#cc6ab5"}, "udtaper": {"text": "걸플갤", "color": "#cc6ab5"}, "un93rgj83g": {"text": "걸플갤", "color": "#cc6ab5"}, "undergo8831": {"text": "걸플갤", "color": "#cc6ab5"}, "uneasy5213": {"text": "걸플갤", "color": "#cc6ab5"}, "unicorn8498": {"text": "걸플갤", "color": "#cc6ab5"}, "unit9235": {"text": "걸플갤", "color": "#cc6ab5"}, "unless8796": {"text": "걸플갤", "color": "#cc6ab5"}, "upset7116": {"text": "걸플갤", "color": "#cc6ab5"}, "urgent4886": {"text": "걸플갤", "color": "#cc6ab5"}, "utilize8504": {"text": "걸플갤", "color": "#cc6ab5"}, "v5050": {"text": "걸플갤", "color": "#cc6ab5"}, "v6xmwml1rw6x1": {"text": "걸플갤", "color": "#cc6ab5"}, "vending1094": {"text": "걸플갤", "color": "#cc6ab5"}, "venture7301": {"text": "걸플갤", "color": "#cc6ab5"}, "venus4326": {"text": "걸플갤", "color": "#cc6ab5"}, "victory9600": {"text": "걸플갤", "color": "#cc6ab5"}, "vietnam0053": {"text": "걸플갤", "color": "#cc6ab5"}, "view9070": {"text": "걸플갤", "color": "#cc6ab5"}, "villager6294": {"text": "걸플갤", "color": "#cc6ab5"}, "virtual6596": {"text": "걸플갤", "color": "#cc6ab5"}, "visiting9307": {"text": "걸플갤", "color": "#cc6ab5"}, "vlslrdh11": {"text": "걸플갤", "color": "#cc6ab5"}, "vmflrjfndl": {"text": "걸플갤", "color": "#cc6ab5"}, "vnvnvnq": {"text": "걸플갤", "color": "#cc6ab5"}, "volume6890": {"text": "걸플갤", "color": "#cc6ab5"}, "voszhqkrwp": {"text": "걸플갤", "color": "#cc6ab5"}, "wall0429": {"text": "걸플갤", "color": "#cc6ab5"}, "wallet2857": {"text": "걸플갤", "color": "#cc6ab5"}, "warmth4373": {"text": "걸플갤", "color": "#cc6ab5"}, "warmth8268": {"text": "걸플갤", "color": "#cc6ab5"}, "warning9019": {"text": "걸플갤", "color": "#cc6ab5"}, "web115131": {"text": "걸플갤", "color": "#cc6ab5"}, "weight4392": {"text": "걸플갤", "color": "#cc6ab5"}, "weird2007": {"text": "걸플갤", "color": "#cc6ab5"}, "whale3490": {"text": "걸플갤", "color": "#cc6ab5"}, "which6900": {"text": "걸플갤", "color": "#cc6ab5"}, "whistle2485": {"text": "걸플갤", "color": "#cc6ab5"}, "whitepetal": {"text": "걸플갤", "color": "#cc6ab5"}, "whom2389": {"text": "걸플갤", "color": "#cc6ab5"}, "wide7506": {"text": "걸플갤", "color": "#cc6ab5"}, "wind9947": {"text": "걸플갤", "color": "#cc6ab5"}, "winter2635": {"text": "걸플갤", "color": "#cc6ab5"}, "wire0490": {"text": "걸플갤", "color": "#cc6ab5"}, "withdraw4648": {"text": "걸플갤", "color": "#cc6ab5"}, "without0736": {"text": "걸플갤", "color": "#cc6ab5"}, "wkadldhk22": {"text": "걸플갤", "color": "#cc6ab5"}, "wkbljs": {"text": "걸플갤", "color": "#cc6ab5"}, "wlq894": {"text": "걸플갤", "color": "#cc6ab5"}, "wns8364": {"text": "걸플갤", "color": "#cc6ab5"}, "wonder7045": {"text": "걸플갤", "color": "#cc6ab5"}, "wony1729": {"text": "걸플갤", "color": "#cc6ab5"}, "wooga0720": {"text": "걸플갤", "color": "#cc6ab5"}, "wool5801": {"text": "걸플갤", "color": "#cc6ab5"}, "work2578": {"text": "걸플갤", "color": "#cc6ab5"}, "working8248": {"text": "걸플갤", "color": "#cc6ab5"}, "wound0905": {"text": "걸플갤", "color": "#cc6ab5"}, "x8qcf8by2dmq": {"text": "걸플갤", "color": "#cc6ab5"}, "xlkmv6fqcn7p": {"text": "걸플갤", "color": "#cc6ab5"}, "xortlemfkdlqj": {"text": "걸플갤", "color": "#cc6ab5"}, "yangilsu830628": {"text": "걸플갤", "color": "#cc6ab5"}, "ybidtmp0bhv9": {"text": "걸플갤", "color": "#cc6ab5"}, "ybk1996": {"text": "걸플갤", "color": "#cc6ab5"}, "yeolgoon": {"text": "걸플갤", "color": "#cc6ab5"}, "yeomseok": {"text": "걸플갤", "color": "#cc6ab5"}, "yeonhye0235": {"text": "걸플갤", "color": "#cc6ab5"}, "yescliff": {"text": "걸플갤", "color": "#cc6ab5"}, "yikes27": {"text": "걸플갤", "color": "#cc6ab5"}, "ysownw": {"text": "걸플갤", "color": "#cc6ab5"}, "yujinzone": {"text": "걸플갤", "color": "#cc6ab5"}, "yzp1yg52poez": {"text": "걸플갤", "color": "#cc6ab5"}, "z37r8vngwq5m": {"text": "걸플갤", "color": "#cc6ab5"}, "zahun322": {"text": "걸플갤", "color": "#cc6ab5"}, "zealotsimon": {"text": "걸플갤", "color": "#cc6ab5"}, "zennyrtlove": {"text": "걸플갤", "color": "#cc6ab5"}, "zizou2621": {"text": "걸플갤", "color": "#cc6ab5"}, "zxcv1qa": {"text": "걸플갤", "color": "#cc6ab5"}}, "NICK": {}, "IP": {}}
